scaffoldfitter/__init__.py
scaffoldfitter/fitter.py
scaffoldfitter/fitterexceptions.py
scaffoldfitter/fitterjson.py
scaffoldfitter/fitterstep.py
scaffoldfitter/fitterstepalign.py
scaffoldfitter/fitterstepconfig.py
scaffoldfitter/fitterstepfit.py
scaffoldfitter-0.11.2.dist-info/licenses/LICENSE
scaffoldfitter-0.11.2.dist-info/METADATA
scaffoldfitter-0.11.2.dist-info/WHEEL
scaffoldfitter-0.11.2.dist-info/top_level.txt
scaffoldfitter-0.11.2.dist-info/RECORD
