Metadata-Version: 2.4
Name: scaffoldfitter
Version: 0.11.2
Summary: Scaffold/model geometric fitting library using Zinc.
Author-email: Richard Christie <r.christie@auckland.ac.nz>
License: 
Keywords: Medical,Physiology,Anatomical,Mesh,Finite Element,Fitting,SPARC
Classifier: Programming Language :: Python :: 3
Classifier: License :: OSI Approved :: Apache Software License
Classifier: Operating System :: OS Independent
Classifier: Topic :: Scientific/Engineering :: Medical Science Apps.
Requires-Python: >=3.8
License-File: LICENSE
Requires-Dist: cmlibs.maths>=0.6.2
Requires-Dist: cmlibs.utils>=0.12.0
Requires-Dist: cmlibs.zinc>=4.1
Dynamic: license-file
